cyberfloodClient/__init__.py
cyberfloodClient/cyberfloodClient.py
cyberfloodClient/Models/Profile.py
cyberfloodClient/Models/Scenario.py
cyberfloodClient/Models/__init__.py
cyberfloodClient-0.0.7.dist-info/LICENSE
cyberfloodClient-0.0.7.dist-info/METADATA
cyberfloodClient-0.0.7.dist-info/WHEEL
cyberfloodClient-0.0.7.dist-info/top_level.txt
cyberfloodClient-0.0.7.dist-info/RECORD
