Metadata-Version: 2.1
Name: cyberfloodClient
Version: 0.0.7
Summary: A CyberFlood REST API client
Home-page: https://github.com/acastaner/cf-py-cfclient
Author: Arnaud Castaner
Author-email: arnaud.castaner@outlook.com
License: UNKNOWN
Platform: UNKNOWN
Classifier: Programming Language :: Python :: 3
Classifier: License :: OSI Approved :: MIT License
Classifier: Operating System :: OS Independent
